BTM/BTM_Plus.py
BTM/__init__.py
BTM/affy.py
BTM/btm2013.py
BTM/btm_example_data.py
BTM/btm_plus_tool.py
BTM/btm_tool.py
BTM/permutate.py
BTM-1.1.5.dist-info/LICENSE
BTM-1.1.5.dist-info/METADATA
BTM-1.1.5.dist-info/WHEEL
BTM-1.1.5.dist-info/top_level.txt
BTM-1.1.5.dist-info/zip-safe
BTM-1.1.5.dist-info/RECORD
