Metadata-Version: 2.1
Name: BTM
Version: 1.1.5
Summary: Blood Transcription Modules for transcriptomics analysis
Home-page: https://github.com/shuzhao-li/BTM
Author: Shuzhao Li
Author-email: shuzhao.li@gmail.com
License: MIT
Keywords: transcriptomics analysis bioinformatics immunology systems biology
Classifier: Development Status :: 5 - Production/Stable
Classifier: Intended Audience :: Developers
Classifier: Intended Audience :: Science/Research
Classifier: License :: OSI Approved :: MIT License
Classifier: Natural Language :: English
Classifier: Operating System :: OS Independent
Classifier: Programming Language :: Python :: 2.7
Classifier: Topic :: Scientific/Engineering :: Bio-Informatics
Classifier: Topic :: Software Development :: Libraries :: Python Modules
License-File: LICENSE
Requires-Dist: numpy
Requires-Dist: scipy
